pycrdt_sticky_xml-0.12.29.dist-info/METADATA
pycrdt_sticky_xml-0.12.29.dist-info/WHEEL
pycrdt_sticky_xml-0.12.29.dist-info/licenses/LICENSE
pycrdt_sticky_xml/__init__.py
pycrdt_sticky_xml/_array.py
pycrdt_sticky_xml/_awareness.py
pycrdt_sticky_xml/_base.py
pycrdt_sticky_xml/_doc.py
pycrdt_sticky_xml/_map.py
pycrdt_sticky_xml/_provider.py
pycrdt_sticky_xml/_pycrdt.cpython-312-darwin.so
pycrdt_sticky_xml/_pycrdt.pyi
pycrdt_sticky_xml/_sticky_index.py
pycrdt_sticky_xml/_sync.py
pycrdt_sticky_xml/_text.py
pycrdt_sticky_xml/_transaction.py
pycrdt_sticky_xml/_undo.py
pycrdt_sticky_xml/_update.py
pycrdt_sticky_xml/_version.py
pycrdt_sticky_xml/_xml.py
pycrdt_sticky_xml/py.typed
pycrdt_sticky_xml-0.12.29.dist-info/RECORD
