Metadata-Version: 2.4
Name: pycrdt-sticky-xml
Version: 0.12.29
Classifier: Development Status :: 4 - Beta
Classifier: Intended Audience :: Developers
Classifier: License :: OSI Approved :: MIT License
Classifier: Programming Language :: Python
Classifier: Programming Language :: Python :: 3.9
Classifier: Programming Language :: Python :: 3.10
Classifier: Programming Language :: Python :: 3.11
Classifier: Programming Language :: Python :: 3.12
Classifier: Programming Language :: Python :: 3.13
Classifier: Programming Language :: Rust
Classifier: Programming Language :: Python :: Implementation :: CPython
Classifier: Programming Language :: Python :: Implementation :: PyPy
Classifier: Topic :: Software Development :: Libraries
Classifier: Topic :: Text Processing :: Markup :: XML
Requires-Dist: anyio>=4.4.0,<5.0.0
Requires-Dist: importlib-metadata>=3.6 ; python_full_version < '3.10'
Requires-Dist: typing-extensions>=4.14.0 ; python_full_version < '3.11'
License-File: LICENSE
Summary: Python bindings for Yrs with sticky_index support for XML types
Keywords: crdt,xml,sticky-index,collaborative-editing
Author-email: David Brochart <david.brochart@gmail.com>, Joshua Lawrence <josh@velvetfs.com>
Requires-Python: >=3.9
Project-URL: Homepage, https://github.com/yourusername/pycrdt-sticky-xml
Project-URL: Original Project, https://github.com/y-crdt/pycrdt
Project-URL: Bug Tracker, https://github.com/yourusername/pycrdt-sticky-xml/issues
